scuzzie/__init__.py
scuzzie/cli.py
scuzzie/comic.py
scuzzie/exc.py
scuzzie/generator.py
scuzzie/gui.py
scuzzie/models.py
scuzzie/resources.py
scuzzie/templator.py
scuzzie-0.6.0.dist-info/entry_points.txt
scuzzie-0.6.0.dist-info/LICENSE
scuzzie-0.6.0.dist-info/WHEEL
scuzzie-0.6.0.dist-info/METADATA
scuzzie-0.6.0.dist-info/RECORD
