Metadata-Version: 2.1
Name: scuzzie
Version: 0.6.0
Summary: a simple webcomic static site generator
Home-page: https://github.com/backwardspy/scuzzie
License: MIT
Author: backwardspy
Author-email: backwardspy@gmail.com
Requires-Python: >=3.10,<4.0
Classifier: License :: OSI Approved :: MIT License
Classifier: Programming Language :: Python :: 3
Classifier: Programming Language :: Python :: 3.10
Provides-Extra: gui
Requires-Dist: Mako (>=1.2.0,<2.0.0)
Requires-Dist: PySimpleGUI (>=4.60.1,<5.0.0); extra == "gui"
Requires-Dist: click (>=8.1.3,<9.0.0)
Requires-Dist: pydantic (>=1.9.1,<2.0.0)
Requires-Dist: python-slugify (>=6.1.2,<7.0.0)
Requires-Dist: tomli (>=2.0.1,<3.0.0)
Requires-Dist: tomli-w (>=1.0.0,<2.0.0)
Project-URL: Repository, https://github.com/backwardspy/scuzzie
